Workbook
Name IntervaloNomeado1: Cod_receitas!$B$2:$B$15

Sheet Despesas
A1: Data | B1: Descrição | C1: Valor | D1: Tipo | E1: Cod_SubCateg | F1: Cod_categoria
A2: 46047 | B2: Sindico Profissional - APSMART ASSESSORIA CONDOMINIAL EIRE - NF. 1820 SINDICO PROFISSIONAL . | C2: R$ 7.920,00 | D2: 2 | E2: 16 | F2: 1 | G2: {=IF(F2:F1000="","",IFERROR(VLOOKUP(TRIM(F2:F1000),{TRIM(Cod_Categ!B2:B1000),Cod_Categ!A2:A1000},2,FALSE),""))}
A3: 46047 | B3: Repasse Custas / Honorários - GENSKE SOCIEDADE INDIVIDUAL ADVOCA. - NF. 7940. HONORARIOS SUCUBEMCIAIS | C3: R$ 147,10 | D3: 2 | E3: 12 | F3: 8
A4: 46047 | B4: repasse Custas / Honorários - GENSKE SOCIEDADE INDIVIDUAL ADVOCA. - NF. 7771. HONORARIOS | C4: R$ 739,92 | D4: 2 | E4: 12 | F4: 8
A5: 46047 | B5: Repasse Custas / Honorários - GENSKE SOCIEDADE INDIVIDUAL ADVOCA. - NF. 9666. REEMBOLSO DESPESAS | C5: R$ 228,60 | D5: 2 | E5: 12 | F5: 8
A6: 46047 | B6: TAXA DE ADMINISTRAÇÃO REF. JAN/25 NF. 64623 | C6: R$ 5.721,00 | D6: 2 | E6: 29 | F6: 1
A7: 46047 | B7: Assembleias/Reuniões - 99 TECNOLOGIA LTDA | C7: R$ 26,70 | D7: 2 | E7: 19 | F7: 3
A8: 46047 | B8: Serviços de entrega - LOGGI TECNOLOGIA LTD | C8: R$ 81,37 | D8: 2 | E8: 19 | F8: 3
A9: 46047 | B9: Tarifa de Cobrança - bancaria | C9: R$ 932,67 | D9: 2 | E9: 2 | F9: 4
A10: 46047 | B10: DCTF Web - MINISTERIO DA FAZENDA. Ref. 12/2024 | C10: R$ 20.708,16 | D10: 2 | E10: 27 | F10: 1
A11: 46047 | B11: Internet - TELEFONICA BRASIL SA INTERNET 899926115923 . FATURA VIVO | C11: R$ 79,99 | D11: 2 | E11: 21 | F11: 9
A12: 46047 | B12: Consumo de Gas - . COMGAS COMGAS 59426861 . FATURA ATRASADA | C12: R$ 4.663,21 | D12: 2 | E12: 9 | F12: 10
A13: 46047 | B13: Consumo de Gas - . COMGAS COMGAS 59426861 . BOLETO EM ATRASO | C13: R$ 4.544,64 | D13: 2 | E13: 9 | F13: 10
A14: 46047 | B14: Consumo de Gas - . COMGAS COMGAS 59426535 . BOLETO EM ATRASO | C14: R$ 2.131,27 | D14: 2 | E14: 9 | F14: 10
... A856: 46138 | B856: Lavanderia - BRASLIMPO COMERCIAL LTDA - NF. 1426895. | C856: R$ 7.508,35 | D856: 2 | E856: 4 | F856: 6

Sheet Cod_Categ
A1: Cod_categ | B1: Categoria
A2: 1 | B2: CONTRATOS
A3: 2 | B3: IMPOSTOS
A4: 3 | B4: TAXAS
A5: 4 | B5: BANCO
A6: 5 | B6: MANUTENÇÃO
A7: 6 | B7: INSUMOS
A8: 7 | B8: OUTRO
A9: 8 | B9: HONORARIOS
A10: 9 | B10: TELEFONIA
A11: 10 | B11: CONSUMO
A12: 11 | B12: COMPRA EQUIPAMENTO
A13: 12 | B13: SEGURO
... A16: 15 | B16: COMBUSTIVEL

Sheet Cod_SubCat
A1: Cod_SubCat | B1: SubCategoria
A2: 1 | B2: ÁGUA
A3: 2 | B3: BANCO
A4: 3 | B4: ISS
A5: 4 | B5: INSUMOS
A6: 5 | B6: CONTRATO ALARME INCÊNCIDO
A7: 6 | B7: CONTRATO PAULISTANA
A8: 7 | B8: CONTRATO MONTE MORIA
A9: 8 | B9: ENERGIA
A10: 9 | B10: GÁS
A11: 10 | B11: CONTRATO CODFY
A12: 11 | B12: CONTRATO PISCINA
A13: 12 | B13: HONORARIOS GENSKE
... A48: 47 | B48: MANUTENÇÃO PREDIAL

Sheet Receitas
A1: data | B1: cod_receita | C1: Receita | D1: tipo | E1: valor
A2: 45658 | B2: 10 | C2: =IFERROR(VLOOKUP(B2,Cod_receitas!A:B,2,FALSE),"") -> SALDO ANTERIOR ORD | D2: 2 | E2: 96162.51
A3: 45658 | B3: 11 | C3: =IFERROR(VLOOKUP(B3,Cod_receitas!A:B,2,FALSE),"") -> SALDO ANTERIOR FUNDO RESERVA | D3: 1 | E3: 39815.87
A4: 45658 | B4: 12 | C4: =IFERROR(VLOOKUP(B4,Cod_receitas!A:B,2,FALSE),"") -> SALDO ANTERIOR APLICAÇÃO FINANCEIRA | D4: 1 | E4: 0
A5: 45658 | B5: 13 | C5: =IFERROR(VLOOKUP(B5,Cod_receitas!A:B,2,FALSE),"") -> SALDO ANTERIOR IMP/TX | D5: 1 | E5: 31755.86
A6: 45658 | B6: 14 | C6: =IFERROR(VLOOKUP(B6,Cod_receitas!A:B,2,FALSE),"") -> FUNDO MANUTENÇÃO | D6: 1 | E6: 120658.2
A7: 45658 | B7: 1 | C7: =IFERROR(VLOOKUP(B7,Cod_receitas!A:B,2,FALSE),"") -> Ordinaria | D7: 1 | E7: 202695.15
A8: 45658 | B8: 2 | C8: =IFERROR(VLOOKUP(B8,Cod_receitas!A:B,2,FALSE),"") -> FUNDO DE RESERVA | D8: 1 | E8: 7905.69
A9: 45658 | B9: 3 | C9: =IFERROR(VLOOKUP(B9,Cod_receitas!A:B,2,FALSE),"") -> APLICAÇÃO FINANCEIRA | D9: 1 | E9: 0
A10: 45658 | B10: 4 | C10: =IFERROR(VLOOKUP(B10,Cod_receitas!A:B,2,FALSE),"") -> IMPOSTOS/TAXAS | D10: 1 | E10: 88.44
A11: 45658 | B11: 5 | C11: =IFERROR(VLOOKUP(B11,Cod_receitas!A:B,2,FALSE),"") -> PROJETO SEGURANÇA | D11: 1 | E11: 1027.68
A12: 45658 | B12: 9 | C12: =IFERROR(VLOOKUP(B12,Cod_receitas!A:B,2,FALSE),"") -> MINIMERCADO/FEIRA-EVENTOS | D12: 1 | E12: 3765.86
A13: 45658 | B13: 1 | C13: =IFERROR(VLOOKUP(B13,Cod_receitas!A:B,2,FALSE),"") -> Ordinaria | D13: 2 | E13: 260078.03
... A196: 46113 | B196: 17 | C196: =IFERROR(VLOOKUP(B196,Cod_receitas!A:B,2,FALSE),"") -> LAVANDERIA | D196: 2 | E196: 7508.35

Sheet Tipo
A1: Cod_tipo | B1: Descrição
A2: 1 | B2: Crédito
A3: 2 | B3: Débito

Sheet Cod_receitas
A1: Cod_RE | B1: Receitas
A2: 1 | B2: Ordinaria
A3: 2 | B3: FUNDO DE RESERVA
A4: 3 | B4: APLICAÇÃO FINANCEIRA
A5: 4 | B5: IMPOSTOS/TAXAS
A6: 5 | B6: PROJETO SEGURANÇA
A7: 6 | B7: ESPACO DE FESTAS
A8: 7 | B8: CONSUMOS
A9: 8 | B9: LAVANDERIA
A10: 9 | B10: MINIMERCADO/FEIRA-EVENTOS
A11: 10 | B11: SALDO ANTERIOR ORD
A12: 11 | B12: SALDO ANTERIOR FUNDO RESERVA
A13: 12 | B13: SALDO ANTERIOR APLICAÇÃO FINANCEIRA
... A20: 19 | B20: ---
